{
    "userdata": [
        {
            "user_id": 100000000000000000,
            "cash": 100.0,
            "items": "none"
        },
        {
            "user_id": 185112370996183042,
            "cash": 5000,
            "engagement": 0,
            "items": [
                [
                    "test_card",
                    6
                ],
                [
                    "test_card3",
                    1
                ],
                [
                    "test_card2",
                    2
                ]
            ]
        }
    ],
    "variables": [],
    "symbols": [
        {
            "name": "currency_symbol",
            "symbol_emoji": "ball"
        }
    ],
    "items": [
        {
            "name": "test_card",
            "team_name": "test_team",
            "image_location": "/root/BBTCG/assets/Season 16/Basic/DaRedskullzz/Alberto Del Riskull.png",
            "shiney": false,
            "position": "generic",
            "rarity": "common"
        },
        {
            "name": "test_card2",
            "team_name": "test_team",
            "image_location": "/root/BBTCG/assets/Season 16/Basic/DaRedskullzz/Alberto Del Riskull.png",
            "shiney": false,
            "position": "generic",
            "rarity": "uncommon"
        },
        {
            "name": "test_card3",
            "team_name": "test_team",
            "image_location": "/root/BBTCG/assets/Season 16/Basic/DaRedskullzz/Alberto Del Riskull.png",
            "shiney": false,
            "position": "generic",
            "rarity": "rare"
        },
        {
            "name": "Shiney test_card4",
            "team_name": "daredskullzz",
            "image_location": "/root/BBTCG/assets/Season 16/Shiney/DaRedskullzz/Alberto Del Riskull.gif",
            "shiney": true,
            "position": "generic",
            "rarity": "common"
        }
    ],
    "income_roles": [
        {
            "role_id": "136399736224624711",
            "role_income": 11,
            "last_updated": "2023-08-06 18:01:35.508680"
        }
    ]
}